pyplumewrfles/__init__.py
pyplumewrfles/multifluidlab.py
pyplumewrfles/pyplume.py
pyplumewrfles-0.0.3.dist-info/LICENSE
pyplumewrfles-0.0.3.dist-info/METADATA
pyplumewrfles-0.0.3.dist-info/WHEEL
pyplumewrfles-0.0.3.dist-info/top_level.txt
pyplumewrfles-0.0.3.dist-info/RECORD
