Metadata-Version: 2.1
Name: pyplumewrfles
Version: 0.0.3
Summary: python package processing turbulence plume data
Home-page: https://github.com/pyplumecamee/pyplume
Author: Thanh Tran
Author-email: pyplume.camee.utsa@gmail.com
License: UNKNOWN
Project-URL: Bug Tracker, https://github.com/pyplumecamee/pyplume/issues
Platform: UNKNOWN
Classifier: Programming Language :: Python :: 3
Classifier: License :: OSI Approved :: MIT License
Classifier: Operating System :: OS Independent
Requires-Python: >=3.6
License-File: LICENSE
